{"name":"Flatten","type":"COMPOSITE_OPERATION","inputs":[{"name":"Input","primitive_name":"Input"}],"outputs":[{"name":"Output","primitive_name":"Output","flow_state":"UNBOUND"}],"operations":[{"name":"get_shape","primitive_name":"get_shape","type":"PRIMITIVE_OPERATION","aliases":["shape","size","get_size"],"position":{"x":280,"y":43},"inputs":[{"name":"input","primitive_name":"input"}],"outputs":[{"name":"shape","primitive_name":"shape","flow_state":"UNBOUND"}]},{"name":"Product","primitive_name":"product","type":"PRIMITIVE_OPERATION","aliases":["series"],"position":{"x":882,"y":47},"inputs":[{"name":"array","primitive_name":"array"},{"name":"dimension_index","data":0,"shape":[],"type":"INTEGER","primitive_name":"dimension_index","flow_state":"BOOT_SOURCE"},{"name":"keep_dimension","data":false,"shape":[],"type":"BOOLEAN","primitive_name":"keep_dimension","flow_state":"BOOT_SOURCE"}],"outputs":[{"name":"prod_result","primitive_name":"prod_result","flow_state":"UNBOUND"}]},{"name":"expand_one_dimension","primitive_name":"expand_one_dimension","type":"PRIMITIVE_OPERATION","aliases":["extend_one_dimension","increase_one_dimension"],"position":{"x":1428,"y":44},"inputs":[{"name":"input","primitive_name":"input"},{"name":"dimension_index","data":0,"shape":[],"type":"INTEGER","primitive_name":"dimension_index","flow_state":"BOOT_SOURCE"}],"outputs":[{"name":"output","primitive_name":"output","flow_state":"UNBOUND"}]},{"name":"Append Scalar to 1D Array","type":"COMPOSITE_OPERATION","aliases":["Add Scalar to 1D Array","Append Scalar to Vector","Add Scalar to Vector"],"position":{"x":1859,"y":43},"inputs":[{"name":"1D Array","primitive_name":"1D Array"},{"name":"Scalar","data":1,"shape":[],"type":"INTEGER","primitive_name":"Scalar","flow_state":"BOOT_SOURCE"}],"outputs":[{"name":"Output","primitive_name":"Output","flow_state":"UNBOUND"}],"operations":[{"name":"expand_one_dimension","primitive_name":"expand_one_dimension","type":"PRIMITIVE_OPERATION","aliases":["expand","expand_dimension","extend","extend_dimension","extend_one_dimension","increase_dimension","increase_one_dimension"],"position":{"x":563,"y":328},"inputs":[{"name":"input","shape":[],"type":"INTEGER","primitive_name":"input","flow_state":"BOOT_SINK"},{"name":"dimension_index","data":0,"shape":[],"type":"INTEGER","primitive_name":"dimension_index","flow_state":"BOOT_SOURCE"}],"outputs":[{"name":"output","primitive_name":"output","flow_state":"UNBOUND"}]},{"name":"concatenate","primitive_name":"concatenate","type":"PRIMITIVE_OPERATION","aliases":["concat","join","merge"],"position":{"x":1241,"y":45},"inputs":[{"name":"array_1","primitive_name":"array_1"},{"name":"array_2","shape":[1],"type":"INTEGER","primitive_name":"array_2","flow_state":"REF_SINK"},{"name":"dimension_index","data":0,"shape":[],"type":"INTEGER","primitive_name":"dimension_index","flow_state":"BOOT_SOURCE"}],"outputs":[{"name":"concatenated_array","primitive_name":"concatenated_array","flow_state":"UNBOUND"}]}],"links":[{"source":{"operation":"this","data":"Scalar"},"sink":{"operation":"expand_one_dimension","data":"input"},"control_points":[]},{"source":{"operation":"this","data":"1D Array"},"sink":{"operation":"concatenate","data":"array_1"},"control_points":[]},{"source":{"operation":"expand_one_dimension","data":"output"},"sink":{"operation":"concatenate","data":"array_2"},"control_points":[]},{"source":{"operation":"concatenate","data":"concatenated_array"},"sink":{"operation":"this","data":"Output"},"control_points":[]}]},{"name":"reshape","primitive_name":"reshape","type":"PRIMITIVE_OPERATION","aliases":["shape","view"],"position":{"x":2347,"y":271},"inputs":[{"name":"input","primitive_name":"input"},{"name":"new_shape","primitive_name":"new_shape"}],"input_order":[1,0],"outputs":[{"name":"output","primitive_name":"output","flow_state":"UNBOUND"}]}],"links":[{"source":{"operation":"this","data":"Input"},"sink":{"operation":"get_shape","data":"input"},"control_points":[]},{"source":{"operation":"this","data":"Input"},"sink":{"operation":"reshape","data":"input"},"control_points":[{"x":714,"y":378}]},{"source":{"operation":"Append Scalar to 1D Array","data":"Output"},"sink":{"operation":"reshape","data":"new_shape"},"control_points":[]},{"source":{"operation":"reshape","data":"output"},"sink":{"operation":"this","data":"Output"},"control_points":[]},{"source":{"operation":"get_shape","data":"shape"},"sink":{"operation":"Product","data":"array"},"control_points":[]},{"source":{"operation":"Product","data":"prod_result"},"sink":{"operation":"expand_one_dimension","data":"input"},"control_points":[]},{"source":{"operation":"expand_one_dimension","data":"output"},"sink":{"operation":"Append Scalar to 1D Array","data":"1D Array"},"control_points":[]}],"global_constants":[]}
